kbron4u/__init__.py
kbron4u/couses.py
kbron4u/utils.py
kbron4u-0.3.0.dist-info/METADATA
kbron4u-0.3.0.dist-info/WHEEL
kbron4u-0.3.0.dist-info/top_level.txt
kbron4u-0.3.0.dist-info/RECORD
