Metadata-Version: 2.1
Name: kbron4u
Version: 0.3.0
Summary: Una mini-bibliotek para consultar los curzos del Tito S4vitar
Home-page: https://hack4u.io
Author: Gyll Ramyrez
